{
    "serveur": "T2",
    "nombre_de_jeux": 3,
    "mises_totales_avant_commission": "38452 jetons",
    "gains_totaux": "36530 jetons",
    "commission_totale": "1922 jetons",
    "utilisateurs": {
        "1229717382554058762": {
            "username": "clzgapiidor",
            "total_wins": "17530 jetons",
            "total_losses": "10000 jetons",
            "total_bets": "19226 jetons",
            "participation": 3
        },
        "218040465835032576": {
            "username": "chabin_.",
            "total_wins": "19000 jetons",
            "total_losses": "9226 jetons",
            "total_bets": "19226 jetons",
            "participation": 3
        }
    },
    "hôtes": {
        "1164911677632950394": {
            "username": "clikclikboom_",
            "total_bets": "38452 jetons",
            "total_commission": "1922 jetons"
        }
    },
    "croupiers": {}
}